odoo/addons/l10n_br_cnpj_search/README.rst
odoo/addons/l10n_br_cnpj_search/__init__.py
odoo/addons/l10n_br_cnpj_search/__manifest__.py
odoo/addons/l10n_br_cnpj_search/data/serpro_qualificacao.csv
odoo/addons/l10n_br_cnpj_search/i18n/l10n_br_cnpj_search.pot
odoo/addons/l10n_br_cnpj_search/i18n/pt_BR.po
odoo/addons/l10n_br_cnpj_search/models/__init__.py
odoo/addons/l10n_br_cnpj_search/models/cnpj_webservice.py
odoo/addons/l10n_br_cnpj_search/models/l10n_br_base_party_mixin.py
odoo/addons/l10n_br_cnpj_search/models/res_company.py
odoo/addons/l10n_br_cnpj_search/models/res_config_settings.py
odoo/addons/l10n_br_cnpj_search/readme/CONFIGURE.rst
odoo/addons/l10n_br_cnpj_search/readme/CONTRIBUTORS.rst
odoo/addons/l10n_br_cnpj_search/readme/DESCRIPTION.rst
odoo/addons/l10n_br_cnpj_search/readme/HISTORY.rst
odoo/addons/l10n_br_cnpj_search/readme/INSTALL.rst
odoo/addons/l10n_br_cnpj_search/readme/ROADMAP.rst
odoo/addons/l10n_br_cnpj_search/readme/USAGE.rst
odoo/addons/l10n_br_cnpj_search/security/ir.model.access.csv
odoo/addons/l10n_br_cnpj_search/static/description/icon.png
odoo/addons/l10n_br_cnpj_search/static/description/index.html
odoo/addons/l10n_br_cnpj_search/static/description/receita.png
odoo/addons/l10n_br_cnpj_search/static/description/receita1.png
odoo/addons/l10n_br_cnpj_search/static/description/receita2.png
odoo/addons/l10n_br_cnpj_search/static/description/serpro.png
odoo/addons/l10n_br_cnpj_search/static/description/serpro1.png
odoo/addons/l10n_br_cnpj_search/tests/__init__.py
odoo/addons/l10n_br_cnpj_search/tests/common.py
odoo/addons/l10n_br_cnpj_search/tests/test_receitaws.py
odoo/addons/l10n_br_cnpj_search/tests/test_serpro.py
odoo/addons/l10n_br_cnpj_search/tests/fixtures/test_receitaws_empresa.yaml
odoo/addons/l10n_br_cnpj_search/tests/fixtures/test_receitaws_multiplos_telefones.yaml
odoo/addons/l10n_br_cnpj_search/tests/fixtures/test_receitaws_not_found.yaml
odoo/addons/l10n_br_cnpj_search/tests/fixtures/test_serpro_basica.yaml
odoo14_addon_l10n_br_cnpj_search-14.0.1.7.3.dist-info/METADATA
odoo14_addon_l10n_br_cnpj_search-14.0.1.7.3.dist-info/WHEEL
odoo14_addon_l10n_br_cnpj_search-14.0.1.7.3.dist-info/top_level.txt
odoo14_addon_l10n_br_cnpj_search-14.0.1.7.3.dist-info/RECORD
