Metadata-Version: 2.1
Name: odoo14-addon-l10n_br_cnpj_search
Version: 14.0.1.7.3
Summary: Integração com os Webservices da ReceitaWS e SerPro
Home-page: https://github.com/OCA/l10n-brazil
Author: KMEE,Odoo Community Association (OCA)
Author-email: support@odoo-community.org
License: AGPL-3
Classifier: Programming Language :: Python
Classifier: Framework :: Odoo
Classifier: Framework :: Odoo :: 14.0
Classifier: License :: OSI Approved :: GNU Affero General Public License v3
Requires-Python: >=3.6
Requires-Dist: erpbrasil.base
Requires-Dist: odoo14-addon-l10n-br-fiscal
Requires-Dist: odoo14-addon-l10n-br-zip
Requires-Dist: odoo<14.1dev,>=14.0a
